command/__init__.py
command/config.json
command/_util/__init__.py
command/_util/_core.py
command/_util/_json.py
command/_util/_progress.py
command/_util/_strutil.py
command/idrearrange/__init__.py
command/idrearrange/_core.py
command/layerauto/__init__.py
command/layerauto/_core.py
command/layermapauto/__init__.py
command/layermapauto/_core.py
command/layerobauto/__init__.py
command/layerobauto/_core.py
command/objectgroupauto/__init__.py
command/objectgroupauto/_core.py
command/objectgroupauto/_data/__init__.py
command/objectgroupauto/_data/_building.py
command/objectgroupauto/_data/_const.py
command/objectgroupauto/_data/_core.py
command/objectgroupauto/_data/_dictionary.py
command/objectgroupauto/_data/_flash.py
command/objectgroupauto/_data/_idcheck.py
command/objectgroupauto/_data/_inadd.py
command/objectgroupauto/_data/_mtext.py
command/objectgroupauto/_data/_multiAdd.py
command/objectgroupauto/_data/_multiRemove.py
command/objectgroupauto/_data/_multiText.py
command/objectgroupauto/_data/_numDetect.py
command/objectgroupauto/_data/_object.py
command/objectgroupauto/_data/_step.py
command/objectgroupauto/_data/_teamDetect.py
command/objectgroupauto/_data/_time.py
command/objectgroupauto/_data/_tree.py
command/resizeauto/__init__.py
command/resizeauto/_core.py
command/stellaris/__init__.py
command/stellaris/_core.py
command/stellaris/new_stellaris/__init__.py
command/stellaris/new_stellaris/_core.py
command/stellaris/stellaris_v10/__init__.py
command/stellaris/stellaris_v10/_core.py
command/stellaris/stellaris_v101/__init__.py
command/stellaris/stellaris_v101/_core.py
command/stellaris/stellaris_v11/__init__.py
command/stellaris/stellaris_v11/_core.py
command/tilesetauto/__init__.py
command/tilesetauto/_core.py
command/tsindep/__init__.py
command/tsindep/_core.py
rwmap/__init__.py
rwmap/_core.py
rwmap/_exceptions.py
rwmap/_case/__init__.py
rwmap/_case/_imagelayer.py
rwmap/_case/_layer.py
rwmap/_case/_object.py
rwmap/_case/_objectgroup.py
rwmapeditor_exgcdwu-1.8.7.3.dist-info/licenses/LICENSE
rwmapeditor_exgcdwu-1.8.7.3.dist-info/METADATA
rwmapeditor_exgcdwu-1.8.7.3.dist-info/WHEEL
rwmapeditor_exgcdwu-1.8.7.3.dist-info/entry_points.txt
rwmapeditor_exgcdwu-1.8.7.3.dist-info/top_level.txt
rwmapeditor_exgcdwu-1.8.7.3.dist-info/RECORD
