Metadata-Version: 2.4
Name: rwmapeditor_exgcdwu
Version: 1.8.7.3
Home-page: https://github.com/exgcdwu/Rusted-Warfare-map-editor-for-city-occupation-play-
Author: exgcdwu
Author-email: 1006605318@qq.com
License:                     GNU GENERAL PUBLIC LICENSE
Requires-Python: >=3.6.0
License-File: LICENSE
Requires-Dist: numpy>=1.26.4
Requires-Dist: Pillow>=10.3.0
Requires-Dist: setuptools>=69.2.0
Requires-Dist: asteval>=0.9.33
Requires-Dist: regex>=2024.7.24
Requires-Dist: pybind11>=2.13.6
Requires-Dist: pybind11_global>=2.13.6
Requires-Dist: imageio>=2.36.0
Requires-Dist: opencv-python>=4.10.0.84
Requires-Dist: scipy>=1.13.1
Requires-Dist: networkx>=3.4.2
Requires-Dist: sortedcontainers>=2.4.0
Requires-Dist: matplotlib>=3.9.2
Dynamic: author
Dynamic: author-email
Dynamic: description
Dynamic: description-content-type
Dynamic: home-page
Dynamic: license
Dynamic: license-file
Dynamic: requires-dist
Dynamic: requires-python
